openfisca_tools/__init__.py
openfisca_tools/hypothetical.py
openfisca_tools/microsimulation.py
openfisca_tools/reforms.py
openfisca_tools/data/__init__.py
openfisca_tools/data/cli.py
openfisca_tools/data/dataset.py
openfisca_tools/data/private.py
openfisca_tools/data/public.py
openfisca_tools/model_api/__init__.py
openfisca_tools/model_api/defined_for.py
openfisca_tools/model_api/index_.py
openfisca_tools/model_api/model_api.py
openfisca_tools/model_api/use_current_parameters.py
openfisca_tools/parameters/__init__.py
openfisca_tools/parameters/interpolation.py
openfisca_tools/parameters/nesting.py
openfisca_tools/parameters/propagation.py
openfisca_tools/parameters/uprating.py
openfisca_tools/testing/__init__.py
openfisca_tools/testing/parameters.py
OpenFisca_Tools-0.13.8.dist-info/METADATA
OpenFisca_Tools-0.13.8.dist-info/WHEEL
OpenFisca_Tools-0.13.8.dist-info/top_level.txt
OpenFisca_Tools-0.13.8.dist-info/RECORD
