Metadata-Version: 2.1
Name: OpenFisca-Tools
Version: 0.13.8
Summary: UNKNOWN
Home-page: https://github.com/policyengine/openfisca-tools
Author: PolicyEngine
License: http://www.fsf.org/licensing/licenses/agpl-3.0.html
Platform: UNKNOWN
Requires-Dist: OpenFisca-Core
Requires-Dist: microdf-python
Requires-Dist: numpy
Requires-Dist: pandas
Requires-Dist: wheel
Requires-Dist: h5py
Requires-Dist: tables
Requires-Dist: google-cloud-storage
Provides-Extra: test
Requires-Dist: OpenFisca-US (>=0.35.0) ; extra == 'test'
Requires-Dist: OpenFisca-UK (>=0.12.0) ; extra == 'test'
